graphiti_core/__init__.py
graphiti_core/decorators.py
graphiti_core/edges.py
graphiti_core/errors.py
graphiti_core/graph_queries.py
graphiti_core/graphiti.py
graphiti_core/graphiti_types.py
graphiti_core/helpers.py
graphiti_core/nodes.py
graphiti_core/py.typed
graphiti_core/tracer.py
graphiti_core/cross_encoder/__init__.py
graphiti_core/cross_encoder/bge_reranker_client.py
graphiti_core/cross_encoder/client.py
graphiti_core/cross_encoder/gemini_reranker_client.py
graphiti_core/cross_encoder/openai_reranker_client.py
graphiti_core/driver/__init__.py
graphiti_core/driver/driver.py
graphiti_core/driver/falkordb_driver.py
graphiti_core/driver/kuzu_driver.py
graphiti_core/driver/neo4j_driver.py
graphiti_core/driver/neptune_driver.py
graphiti_core/driver/graph_operations/graph_operations.py
graphiti_core/driver/search_interface/search_interface.py
graphiti_core/embedder/__init__.py
graphiti_core/embedder/azure_openai.py
graphiti_core/embedder/client.py
graphiti_core/embedder/gemini.py
graphiti_core/embedder/openai.py
graphiti_core/embedder/voyage.py
graphiti_core/llm_client/__init__.py
graphiti_core/llm_client/anthropic_client.py
graphiti_core/llm_client/azure_openai_client.py
graphiti_core/llm_client/client.py
graphiti_core/llm_client/config.py
graphiti_core/llm_client/errors.py
graphiti_core/llm_client/gemini_client.py
graphiti_core/llm_client/groq_client.py
graphiti_core/llm_client/openai_base_client.py
graphiti_core/llm_client/openai_client.py
graphiti_core/llm_client/openai_generic_client.py
graphiti_core/llm_client/utils.py
graphiti_core/migrations/__init__.py
graphiti_core/models/__init__.py
graphiti_core/models/edges/__init__.py
graphiti_core/models/edges/edge_db_queries.py
graphiti_core/models/nodes/__init__.py
graphiti_core/models/nodes/node_db_queries.py
graphiti_core/prompts/__init__.py
graphiti_core/prompts/dedupe_edges.py
graphiti_core/prompts/dedupe_nodes.py
graphiti_core/prompts/eval.py
graphiti_core/prompts/extract_edge_dates.py
graphiti_core_varming-0.23.3.dist-info/METADATA
graphiti_core_varming-0.23.3.dist-info/WHEEL
graphiti_core_varming-0.23.3.dist-info/licenses/LICENSE
graphiti_core_varming-0.23.3.dist-info/RECORD
